src/arg_handling.py
src/lfract.py
src/lsystem.py
src/turtle.py
lfract-1.0.0.dist-info/entry_points.txt
lfract-1.0.0.dist-info/LICENSE
lfract-1.0.0.dist-info/WHEEL
lfract-1.0.0.dist-info/METADATA
lfract-1.0.0.dist-info/RECORD
