Metadata-Version: 2.1
Name: lfract
Version: 1.0.0
Summary: An open-source CLI software for generating fractal images using the L-System.
Home-page: https://github.com/SurasithO/lfract
License: MIT
Author: Surasith Boonaneksap
Author-email: surasith.boo@hotmail.com
Requires-Python: >=3.6
Classifier: License :: OSI Approved :: MIT License
Classifier: Programming Language :: Python :: 3
Classifier: Programming Language :: Python :: 3.6
Classifier: Programming Language :: Python :: 3.7
Classifier: Programming Language :: Python :: 3.8
Classifier: Programming Language :: Python :: 3.9
Requires-Dist: Pillow (>=4.0)
Project-URL: Documentation, https://github.com/SurasithO/lfract
Project-URL: Repository, https://github.com/SurasithO/lfract
